{
  "_commit": "0d33fca0d1c29c79aef9c7053e36d9e7cdd2bd20",
  "_copy_without_render": [
    "*.rst_t"
  ],
  "_jinja2_env_vars": {
    "lstrip_blocks": true,
    "trim_blocks": true
  },
  "_template": "https://github.com/statisticsnorway/ssb-pypitemplate.git",
  "author": "Roar V\u00e5len",
  "code_quality_level": "Medium",
  "copyright_owner": "Statistics Norway",
  "copyright_year": "2025",
  "development_status": "Development Status :: 4 - Beta",
  "email": "rav@ssb.no",
  "friendly_name": "SSB Pypitest Rav",
  "github_organization": "statisticsnorway",
  "license": "MIT",
  "package_name": "ssb_pypitest_rav",
  "project_name": "ssb-pypitest-rav",
  "version": "0.0.1"
}
